{"type":"category","label":"","path":".","items":[{"type":"category","label":"bilder","path":"bilder","items":[{"type":"category","label":"logo","path":"bilder/logo","items":[{"type":"item","label":"section77","previewImage":{"basename":"gh-pages-preview-section77.png","dirname":"bilder/logo","mtime":1568450971385,"size":9697},"files":[{"basename":"section77.pdf","dirname":"bilder/logo","mtime":1568450971385,"size":2490},{"basename":"section77.png","dirname":"bilder/logo","mtime":1568450971385,"size":30526},{"basename":"section77.svg","dirname":"bilder/logo","mtime":1568450971385,"size":2147}]}]},{"type":"item","label":"stm32f3discovery","previewImage":{"basename":"gh-pages-preview-stm32f3discovery.jpg","dirname":"bilder","mtime":1568450971369,"size":79285},"files":[{"basename":"stm32f3discovery.jpg","dirname":"bilder","mtime":1568450971381,"size":3852491}]},{"type":"item","label":"source-code","previewImage":{"basename":"gh-pages-preview-source-code.png","dirname":"bilder","mtime":1568450971369,"size":49126},"files":[{"basename":"source-code.png","dirname":"bilder","mtime":1568450971369,"size":62611}]},{"type":"item","label":"esp32","previewImage":{"basename":"gh-pages-preview-esp32.jpg","dirname":"bilder","mtime":1568450971369,"size":41513},"files":[{"basename":"esp32.jpg","dirname":"bilder","mtime":1568450971369,"size":3207581}]},{"type":"item","label":"eggbot","previewImage":{"basename":"gh-pages-preview-eggbot.jpg","dirname":"bilder","mtime":1568450971369,"size":38188},"files":[{"basename":"eggbot.jpg","dirname":"bilder","mtime":1568450971357,"size":2858601}]},{"type":"item","label":"blue-pill","previewImage":{"basename":"gh-pages-preview-blue-pill.jpg","dirname":"bilder","mtime":1568450971369,"size":41283},"files":[{"basename":"blue-pill.jpg","dirname":"bilder","mtime":1568450971345,"size":3201805}]}]},{"type":"category","label":"bürger-büro-offenburg","path":"bürger-büro-offenburg","items":[{"type":"category","label":"2019","path":"bürger-büro-offenburg/2019","items":[{"type":"item","label":"mitmachwerkstatt","previewImage":{"basename":"gh-pages-preview-mitmachwerkstatt.png","dirname":"bürger-büro-offenburg/2019","mtime":1568450971385,"size":467876},"files":[{"basename":"mitmachwerkstatt.ai","dirname":"bürger-büro-offenburg/2019","mtime":1568450971405,"size":5566587},{"basename":"mitmachwerkstatt.pdf","dirname":"bürger-büro-offenburg/2019","mtime":1568450971421,"size":4512683},{"basename":"mitmachwerkstatt.png","dirname":"bürger-büro-offenburg/2019","mtime":1568450971429,"size":2376814}]}]}]},{"type":"category","label":"flyer","path":"flyer","items":[{"type":"category","label":"2019","path":"flyer/2019","items":[{"type":"item","label":"tech-event-maerz-mai-front","previewImage":{"basename":"gh-pages-preview-tech-event-maerz-mai-front.png","dirname":"flyer/2019","mtime":1568450971617,"size":56345},"files":[{"basename":"tech-event-maerz-mai-front.pdf","dirname":"flyer/2019","mtime":1568450971685,"size":125109},{"basename":"tech-event-maerz-mai-front.png","dirname":"flyer/2019","mtime":1568450971685,"size":402994},{"basename":"tech-event-maerz-mai-front.svg","dirname":"flyer/2019","mtime":1568450971685,"size":148311}]},{"type":"item","label":"tech-event-maerz-mai-back","previewImage":{"basename":"gh-pages-preview-tech-event-maerz-mai-back.png","dirname":"flyer/2019","mtime":1568450971617,"size":30660},"files":[{"basename":"tech-event-maerz-mai-back.pdf","dirname":"flyer/2019","mtime":1568450971685,"size":19771},{"basename":"tech-event-maerz-mai-back.png","dirname":"flyer/2019","mtime":1568450971685,"size":212673},{"basename":"tech-event-maerz-mai-back.svg","dirname":"flyer/2019","mtime":1568450971685,"size":23589}]},{"type":"item","label":"tech-event-august-oktober-front","previewImage":{"basename":"gh-pages-preview-tech-event-august-oktober-front.png","dirname":"flyer/2019","mtime":1568450971617,"size":129194},"files":[{"basename":"tech-event-august-oktober-front.png","dirname":"flyer/2019","mtime":1568450971681,"size":289522},{"basename":"tech-event-august-oktober-front.pdf","dirname":"flyer/2019","mtime":1568450971681,"size":1024076}]},{"type":"item","label":"tech-event-august-oktober-back","previewImage":{"basename":"gh-pages-preview-tech-event-august-oktober-back.png","dirname":"flyer/2019","mtime":1568450971613,"size":139633},"files":[{"basename":"tech-event-august-oktober-back.png","dirname":"flyer/2019","mtime":1568450971677,"size":472591},{"basename":"tech-event-august-oktober-back.pdf","dirname":"flyer/2019","mtime":1568450971677,"size":10714403}]},{"type":"item","label":"mitmachwerkstatt-front","previewImage":{"basename":"gh-pages-preview-mitmachwerkstatt-front.png","dirname":"flyer/2019","mtime":1568450971613,"size":151453},"files":[{"basename":"mitmachwerkstatt-front.pdf","dirname":"flyer/2019","mtime":1568450971633,"size":2997033},{"basename":"mitmachwerkstatt-front.png","dirname":"flyer/2019","mtime":1568450971637,"size":988735}]},{"type":"item","label":"mitmachwerkstatt-back","previewImage":{"basename":"gh-pages-preview-mitmachwerkstatt-back.png","dirname":"flyer/2019","mtime":1568450971613,"size":93298},"files":[{"basename":"mitmachwerkstatt-back.png","dirname":"flyer/2019","mtime":1568450971625,"size":738751},{"basename":"mitmachwerkstatt-back.pdf","dirname":"flyer/2019","mtime":1568450971621,"size":1327536}]},{"type":"item","label":"2019-09-21 - Freies Hacken","previewImage":{"basename":"gh-pages-preview-2019-09-21 - Freies Hacken.png","dirname":"flyer/2019","mtime":1568450971613,"size":98237},"files":[{"basename":"2019-09-21 - Freies Hacken.xcf","dirname":"flyer/2019","mtime":1568450971613,"size":30319742},{"basename":"2019-09-21 - Freies Hacken.png","dirname":"flyer/2019","mtime":1568450971505,"size":9463771}]},{"type":"item","label":"2019-09-21 - Freies Hacken-3zu2","previewImage":{"basename":"gh-pages-preview-2019-09-21 - Freies Hacken-3zu2.png","dirname":"flyer/2019","mtime":1568450971613,"size":91265},"files":[{"basename":"2019-09-21 - Freies Hacken-3zu2.png","dirname":"flyer/2019","mtime":1568450971469,"size":11443298}]}]}]},{"type":"category","label":"poster","path":"poster","items":[{"type":"category","label":"2019","path":"poster/2019","items":[{"type":"item","label":"tech-event-maerz-mai","previewImage":{"basename":"gh-pages-preview-tech-event-maerz-mai.png","dirname":"poster/2019","mtime":1568450971689,"size":106720},"files":[{"basename":"tech-event-maerz-mai.pdf","dirname":"poster/2019","mtime":1568450971793,"size":335695},{"basename":"tech-event-maerz-mai.png","dirname":"poster/2019","mtime":1568450971801,"size":2281451},{"basename":"tech-event-maerz-mai.svg","dirname":"poster/2019","mtime":1568450971801,"size":738432}]},{"type":"item","label":"mitmachwerkstatt","previewImage":{"basename":"gh-pages-preview-mitmachwerkstatt.png","dirname":"poster/2019","mtime":1568450971689,"size":162824},"files":[{"basename":"mitmachwerkstatt.pdf","dirname":"poster/2019","mtime":1568450971773,"size":23963721},{"basename":"mitmachwerkstatt.png","dirname":"poster/2019","mtime":1568450971789,"size":4388350}]}]}]}]}